{
  "summary": {
    "total": 100,
    "keep": 6,
    "update": 0,
    "remove": 0,
    "review": 94
  },
  "assessments": {
    "KEEP": [
      {
        "formula": "deff= 12 + 0.5 × (α₄ + α₅) = 12 + 0.5 × 1.1781 = 12.589",
        "category": "other",
        "file": "sections/cosmology.html",
        "action": "KEEP",
        "reason": "Shared dimensions from TCS G₂ construction",
        "simulation_backed": true,
        "pm_values": [
          "d_eff",
          "alpha_4",
          "alpha_5",
          "w0_from_d_eff"
        ]
      },
      {
        "formula": "w0= -(deff- 1)/(deff+ 1) = -(12.589 - 1)/(12.589 + 1) =",
        "category": "other",
        "file": "sections/cosmology.html",
        "action": "KEEP",
        "reason": "Shared dimensions from TCS G₂ construction",
        "simulation_backed": true,
        "pm_values": [
          "d_eff",
          "alpha_4",
          "alpha_5",
          "w0_from_d_eff"
        ]
      },
      {
        "formula": "w0= -(Deff- 1)/(Deff+ 1) = -(12.589 - 1)/(12.589 + 1) =± 0.001where Deff= 12 + 0.589 from quantum co",
        "category": "other",
        "file": "sections/cosmology.html",
        "action": "KEEP",
        "reason": "Shared dimensions from TCS G₂ construction",
        "simulation_backed": true,
        "pm_values": [
          "d_eff",
          "alpha_4",
          "alpha_5",
          "w0_from_d_eff"
        ]
      },
      {
        "formula": "Deff= 12 + δDquantum= 12 + 0.589 =12.589",
        "category": "other",
        "file": "sections/cosmology.html",
        "action": "KEEP",
        "reason": "Shared dimensions from TCS G₂ construction",
        "simulation_backed": true,
        "pm_values": [
          "d_eff",
          "alpha_4",
          "alpha_5",
          "w0_from_d_eff"
        ]
      },
      {
        "formula": "w0= -(12.589 - 1)/(12.589 + 1) = -11.589/13.589 =± 0.001",
        "category": "other",
        "file": "sections/cosmology.html",
        "action": "KEEP",
        "reason": "Shared dimensions from TCS G₂ construction",
        "simulation_backed": true,
        "pm_values": [
          "d_eff",
          "alpha_4",
          "alpha_5",
          "w0_from_d_eff"
        ]
      },
      {
        "formula": "Θ' ≤ -(Θ2/2) - 8πG⟨Tkk⟩ren(6.16)",
        "category": "other",
        "file": "sections/cosmology.html",
        "action": "KEEP",
        "reason": "KK spectrum from kk_spectrum_full.py simulation",
        "simulation_backed": true,
        "pm_values": [
          "m1",
          "m2",
          "m3",
          "BR_gg",
          "BR_qq"
        ]
      }
    ],
    "UPDATE": [],
    "REMOVE": [],
    "REVIEW": [
      {
        "formula": "V(φ) = -(m²/2)φ² + (λ/4)φ⁴ + V₀",
        "category": "other",
        "file": "sections/cmb-bubble-collisions-comprehensive.html",
        "action": "REVIEW",
        "reason": "Needs manual review",
        "simulation_backed": false
      },
      {
        "formula": "Γ ~ (Δφ)⁴ exp(-B),    B = (2/ℏ) ∫φfalseφturn√[2m(V(φ) - Vfalse)] dφ",
        "category": "other",
        "file": "sections/cmb-bubble-collisions-comprehensive.html",
        "action": "REVIEW",
        "reason": "Needs manual review",
        "simulation_backed": false
      },
      {
        "formula": "SE= 2π² ∫ [ρ³((dφ/dr)²/2 + V(φ)) + 3ρ(dρ/dr)²/(8πG) - 3ρ/(8πG)] dr",
        "category": "other",
        "file": "sections/cmb-bubble-collisions-comprehensive.html",
        "action": "REVIEW",
        "reason": "Needs manual review",
        "simulation_backed": false
      },
      {
        "formula": "rb= 3σ/(4ΔV)(7.7.1)",
        "category": "other",
        "file": "sections/cmb-bubble-collisions-comprehensive.html",
        "action": "REVIEW",
        "reason": "Needs manual review",
        "simulation_backed": false
      },
      {
        "formula": "SE= 27π²σ⁴/(2ΔV³)(7.7.2)",
        "category": "other",
        "file": "sections/cmb-bubble-collisions-comprehensive.html",
        "action": "REVIEW",
        "reason": "Needs manual review",
        "simulation_backed": false
      },
      {
        "formula": "Γ ~ exp(-SE)(7.7.3)",
        "category": "other",
        "file": "sections/cmb-bubble-collisions-comprehensive.html",
        "action": "REVIEW",
        "reason": "Needs manual review",
        "simulation_backed": false
      },
      {
        "formula": "P(δ > δ₀) = exp(-n · A · exp[-δ₀²/(2σ²)])",
        "category": "other",
        "file": "sections/cmb-bubble-collisions-comprehensive.html",
        "action": "REVIEW",
        "reason": "Needs manual review",
        "simulation_backed": false
      },
      {
        "formula": "ζ ~ -(rbH)1/2",
        "category": "other",
        "file": "sections/cmb-bubble-collisions-comprehensive.html",
        "action": "REVIEW",
        "reason": "Needs manual review",
        "simulation_backed": false
      },
      {
        "formula": "ΔT/T ~ ζ/5 ~ -(rbH)1/2/5(7.7.4)",
        "category": "other",
        "file": "sections/cmb-bubble-collisions-comprehensive.html",
        "action": "REVIEW",
        "reason": "Needs manual review",
        "simulation_backed": false
      },
      {
        "formula": "P(Nspots) = λNexp(-λ) / N!",
        "category": "other",
        "file": "sections/cmb-bubble-collisions-comprehensive.html",
        "action": "REVIEW",
        "reason": "Needs manual review",
        "simulation_backed": false
      },
      {
        "formula": "κ = ⟨(ΔT)⁴⟩ / ⟨(ΔT)²⟩² = 3 + Nspots(δdisk)⁴/σ⁴(7.7.5)",
        "category": "other",
        "file": "sections/cmb-bubble-collisions-comprehensive.html",
        "action": "REVIEW",
        "reason": "Needs manual review",
        "simulation_backed": false
      },
      {
        "formula": "Γ/V₄ = A exp(-SE[φbounce])",
        "category": "other",
        "file": "sections/cmb-bubble-collisions-comprehensive.html",
        "action": "REVIEW",
        "reason": "Needs manual review",
        "simulation_backed": false
      },
      {
        "formula": "SE[φ, g] = ∫ d⁴x √g [(1/2)gμν∂μφ∂νφ + V(φ) - R/(16πG)]",
        "category": "other",
        "file": "sections/cmb-bubble-collisions-comprehensive.html",
        "action": "REVIEW",
        "reason": "Needs manual review",
        "simulation_backed": false
      },
      {
        "formula": "ds² = dξ² + ρ(ξ)² dΩ₃²",
        "category": "other",
        "file": "sections/cmb-bubble-collisions-comprehensive.html",
        "action": "REVIEW",
        "reason": "Needs manual review",
        "simulation_backed": false
      },
      {
        "formula": "Ewall= 4πrb²σ    (surface energy)",
        "category": "other",
        "file": "sections/cmb-bubble-collisions-comprehensive.html",
        "action": "REVIEW",
        "reason": "Needs manual review",
        "simulation_backed": false
      },
      {
        "formula": "Evolume= -(4π/3)rb³ΔV    (volume energy gain)",
        "category": "other",
        "file": "sections/cmb-bubble-collisions-comprehensive.html",
        "action": "REVIEW",
        "reason": "Needs manual review",
        "simulation_backed": false
      },
      {
        "formula": "rb= 2σ/ΔV",
        "category": "other",
        "file": "sections/cmb-bubble-collisions-comprehensive.html",
        "action": "REVIEW",
        "reason": "Needs manual review",
        "simulation_backed": false
      },
      {
        "formula": "rb= 3σ/(4ΔV)(gravitational correction)",
        "category": "other",
        "file": "sections/cmb-bubble-collisions-comprehensive.html",
        "action": "REVIEW",
        "reason": "Needs manual review",
        "simulation_backed": false
      },
      {
        "formula": "SE= (surface term) + (curvature term) = π²ρ₀³σ - 3π²ρ₀⁴ΔV/4",
        "category": "other",
        "file": "sections/cmb-bubble-collisions-comprehensive.html",
        "action": "REVIEW",
        "reason": "Needs manual review",
        "simulation_backed": false
      },
      {
        "formula": "SE= 27π²σ⁴ / (2ΔV³)(7.8.1)",
        "category": "other",
        "file": "sections/cmb-bubble-collisions-comprehensive.html",
        "action": "REVIEW",
        "reason": "Needs manual review",
        "simulation_backed": false
      },
      {
        "formula": "Γ / V₄ = A(ΔV, σ) · exp(-SE)(7.8.2)",
        "category": "other",
        "file": "sections/cmb-bubble-collisions-comprehensive.html",
        "action": "REVIEW",
        "reason": "Needs manual review",
        "simulation_backed": false
      },
      {
        "formula": "ΔVeff= ΔV / (1 + ηΔtortho)",
        "category": "other",
        "file": "sections/cmb-bubble-collisions-comprehensive.html",
        "action": "REVIEW",
        "reason": "Needs manual review",
        "simulation_backed": false
      },
      {
        "formula": "ds213= gμν(x)dxμdxν+\n            gmn(x,y)dymdyn+ 2Aμa(x)Kamdxμdym(6.1)",
        "category": "other",
        "file": "sections/cosmology.html",
        "action": "REVIEW",
        "reason": "Needs manual review",
        "simulation_backed": false
      },
      {
        "formula": "S14= (1/2κ142) ∫ d14x √(-G) R14(6.2)",
        "category": "other",
        "file": "sections/cosmology.html",
        "action": "REVIEW",
        "reason": "Needs manual review",
        "simulation_backed": false
      },
      {
        "formula": "gmn(x,y) = e2σ(x)gmn(0)(y)(6.4)",
        "category": "other",
        "file": "sections/cosmology.html",
        "action": "REVIEW",
        "reason": "Needs manual review",
        "simulation_backed": false
      },
      {
        "formula": "ds226= GMNdXMdXN,    M,N = 0,1,...,25",
        "category": "other",
        "file": "sections/cosmology.html",
        "action": "REVIEW",
        "reason": "Needs manual review",
        "simulation_backed": false
      },
      {
        "formula": "XM∂MΦ = 0",
        "category": "other",
        "file": "sections/cosmology.html",
        "action": "REVIEW",
        "reason": "Needs manual review",
        "simulation_backed": false
      },
      {
        "formula": "ds214= gμνdxμdxν+ gmndymdyn",
        "category": "other",
        "file": "sections/cosmology.html",
        "action": "REVIEW",
        "reason": "Needs manual review",
        "simulation_backed": false
      },
      {
        "formula": "ttotal= ttherm+ β tortho,    β = cos(θmirror)",
        "category": "other",
        "file": "sections/cosmology.html",
        "action": "REVIEW",
        "reason": "Needs manual review",
        "simulation_backed": false
      },
      {
        "formula": "ctotal= cbulk+ cghosts+ cmatter= 0",
        "category": "other",
        "file": "sections/cosmology.html",
        "action": "REVIEW",
        "reason": "Needs manual review",
        "simulation_backed": false
      },
      {
        "formula": "ctotal= 24 − 26 + 2 =0✓",
        "category": "other",
        "file": "sections/cosmology.html",
        "action": "REVIEW",
        "reason": "Needs manual review",
        "simulation_backed": false
      },
      {
        "formula": "(5,2) + 3×(3,2)",
        "category": "other",
        "file": "sections/cosmology.html",
        "action": "REVIEW",
        "reason": "Needs manual review",
        "simulation_backed": false
      },
      {
        "formula": "TBPS≥ |Zp,q| / Vp",
        "category": "other",
        "file": "sections/cosmology.html",
        "action": "REVIEW",
        "reason": "Needs manual review",
        "simulation_backed": false
      },
      {
        "formula": "∑ Qbranes+ QO-planes= 0    (tadpole cancellation)",
        "category": "other",
        "file": "sections/cosmology.html",
        "action": "REVIEW",
        "reason": "Needs manual review",
        "simulation_backed": false
      },
      {
        "formula": "C2(SO(24,2)) = p(p + 22)/4",
        "category": "other",
        "file": "sections/cosmology.html",
        "action": "REVIEW",
        "reason": "Needs manual review",
        "simulation_backed": false
      },
      {
        "formula": "dimeff= 4 × 16 =64 components",
        "category": "other",
        "file": "sections/cosmology.html",
        "action": "REVIEW",
        "reason": "Needs manual review",
        "simulation_backed": false
      },
      {
        "formula": "S = ∫ d4x √(-g) [φR + ψT - V(φ,ψ)](6.6)",
        "category": "other",
        "file": "sections/cosmology.html",
        "action": "REVIEW",
        "reason": "Needs manual review",
        "simulation_backed": false
      },
      {
        "formula": "Tλμν= Γλ[μν]≠ 0(6.7)",
        "category": "other",
        "file": "sections/cosmology.html",
        "action": "REVIEW",
        "reason": "Needs manual review",
        "simulation_backed": false
      },
      {
        "formula": "Tλμν∼ κ2⟨ΨPγλγ[μγν]ΨP⟩(6.8)",
        "category": "other",
        "file": "sections/cosmology.html",
        "action": "REVIEW",
        "reason": "Needs manual review",
        "simulation_backed": false
      },
      {
        "formula": "F(R,T,τ) = R + αR2+ βT + γRT + δ(∂τ)T(6.8a)",
        "category": "other",
        "file": "sections/cosmology.html",
        "action": "REVIEW",
        "reason": "Needs manual review",
        "simulation_backed": false
      },
      {
        "formula": "Seff= (1/(16π2)) ∫ d4x √-g [a0+ a2R + a4R2+ ...]",
        "category": "other",
        "file": "sections/cosmology.html",
        "action": "REVIEW",
        "reason": "Needs manual review",
        "simulation_backed": false
      },
      {
        "formula": "∫ d4x √-g e2σTmatter→ ∫ d4x √-g (1 + 2σ + ...) T",
        "category": "other",
        "file": "sections/cosmology.html",
        "action": "REVIEW",
        "reason": "Needs manual review",
        "simulation_backed": false
      },
      {
        "formula": "β = 2⟨σ⟩ = 2φ0≈0.15",
        "category": "other",
        "file": "sections/cosmology.html",
        "action": "REVIEW",
        "reason": "Needs manual review",
        "simulation_backed": false
      },
      {
        "formula": "γ = (g2)/(MPl2) × VK-1/2",
        "category": "other",
        "file": "sections/cosmology.html",
        "action": "REVIEW",
        "reason": "Needs manual review",
        "simulation_backed": false
      },
      {
        "formula": "γ ≈10-4/MPl2",
        "category": "other",
        "file": "sections/cosmology.html",
        "action": "REVIEW",
        "reason": "Needs manual review",
        "simulation_backed": false
      },
      {
        "formula": "∫ d26X √-G &barΨ iΓM∂MΨ ⊃ ∫ d4x √-g [(∂t)T + g Δtortho(∂τ)T]",
        "category": "other",
        "file": "sections/cosmology.html",
        "action": "REVIEW",
        "reason": "Needs manual review",
        "simulation_backed": false
      },
      {
        "formula": "δ = g Δtortho≈ 0.1 × 10-18s =10-19s",
        "category": "other",
        "file": "sections/cosmology.html",
        "action": "REVIEW",
        "reason": "Needs manual review",
        "simulation_backed": false
      },
      {
        "formula": "CISW= 1 + (γ/β) × (R/T) × fgrav≈ 1 + (10-4/0.15) × O(1) × 2.3 ≈1.5",
        "category": "other",
        "file": "sections/cosmology.html",
        "action": "REVIEW",
        "reason": "Needs manual review",
        "simulation_backed": false
      },
      {
        "formula": "δT/T ~ β × (δφ/MPl) × (Δθ/10°)-2≈ 0.15 × 0.01 × 10-4≈-70 μKwhere δφ ~ 0.01 MPlis the bubble wall thi",
        "category": "other",
        "file": "sections/cosmology.html",
        "action": "REVIEW",
        "reason": "CMB bubble predictions (testable but not core to v8.4)",
        "simulation_backed": false
      },
      {
        "formula": "ds²6= e-2kyημνdxμdxν+ dy² + dz²(6.9a)",
        "category": "other",
        "file": "sections/cosmology.html",
        "action": "REVIEW",
        "reason": "Needs manual review",
        "simulation_backed": false
      },
      {
        "formula": "Mtower(d) ~ MPle-αd/MPl",
        "category": "other",
        "file": "sections/cosmology.html",
        "action": "REVIEW",
        "reason": "Needs manual review",
        "simulation_backed": false
      },
      {
        "formula": "α > αcrit= √(2/3) ≈0.816",
        "category": "other",
        "file": "sections/cosmology.html",
        "action": "REVIEW",
        "reason": "Needs manual review",
        "simulation_backed": false
      },
      {
        "formula": "a = √(26/13) = √(2) ≈1.414",
        "category": "other",
        "file": "sections/cosmology.html",
        "action": "REVIEW",
        "reason": "Needs manual review",
        "simulation_backed": false
      },
      {
        "formula": "1.414 > 0.816   ✔SWAMPLAND CONSTRAINT SATISFIED",
        "category": "other",
        "file": "sections/cosmology.html",
        "action": "REVIEW",
        "reason": "Needs manual review",
        "simulation_backed": false
      },
      {
        "formula": "V(χ) = V0[1 + (χ/MPl)-α]   \n            (tracker potential)(6.11)",
        "category": "other",
        "file": "sections/cosmology.html",
        "action": "REVIEW",
        "reason": "Needs manual review",
        "simulation_backed": false
      },
      {
        "formula": "x = χ'/(√6 H)    \n          y = √(V/3H2MPl2)    \n          z = √(ρm/3H2MPl2)",
        "category": "other",
        "file": "sections/cosmology.html",
        "action": "REVIEW",
        "reason": "Needs manual review",
        "simulation_backed": false
      },
      {
        "formula": "ρΛ= V0≈ (2.3 × 10-3eV)4(6.14)",
        "category": "other",
        "file": "sections/cosmology.html",
        "action": "REVIEW",
        "reason": "Needs manual review",
        "simulation_backed": false
      },
      {
        "formula": "V0= MPl4× exp(-4αd/MPl)",
        "category": "other",
        "file": "sections/cosmology.html",
        "action": "REVIEW",
        "reason": "Needs manual review",
        "simulation_backed": false
      },
      {
        "formula": "V0= ngen× MPl4/ SdS≈ 3 × 10-46GeV4",
        "category": "other",
        "file": "sections/cosmology.html",
        "action": "REVIEW",
        "reason": "Needs manual review",
        "simulation_backed": false
      },
      {
        "formula": "F(R,T) = R + αR2+ βT + γRTwhere β = 0.15 from breathing mode VEV: φ0= 0.075 MPl",
        "category": "other",
        "file": "sections/cosmology.html",
        "action": "REVIEW",
        "reason": "Needs manual review",
        "simulation_backed": false
      },
      {
        "formula": "Δw0= -β × (Ωm/ΩDE) × CISW≈ -0.15 × 0.43 × 1.5 ≈-0.10",
        "category": "other",
        "file": "sections/cosmology.html",
        "action": "REVIEW",
        "reason": "Needs manual review",
        "simulation_backed": false
      },
      {
        "formula": "w0= -(Deff- 1)/(Deff+ 1)",
        "category": "other",
        "file": "sections/cosmology.html",
        "action": "REVIEW",
        "reason": "Needs manual review",
        "simulation_backed": false
      },
      {
        "formula": "Lint= (g/f) (∂μχ) JμPneumaProtected by approximate shift symmetry χ → χ + const",
        "category": "other",
        "file": "sections/cosmology.html",
        "action": "REVIEW",
        "reason": "Needs manual review",
        "simulation_backed": false
      },
      {
        "formula": "αT(z) = 1 + (3/2) × fm(z)where fm(z) = Ωm(1+z)3/ [Ωm(1+z)3+ ΩΛ]",
        "category": "other",
        "file": "sections/cosmology.html",
        "action": "REVIEW",
        "reason": "Needs manual review",
        "simulation_backed": false
      },
      {
        "formula": "ρ'm+ 3Hρm= -Q     \n            ρ'χ+ 3H(1+w)ρχ= +Q(6.15e)",
        "category": "other",
        "file": "sections/cosmology.html",
        "action": "REVIEW",
        "reason": "Needs manual review",
        "simulation_backed": false
      },
      {
        "formula": "gμν= ημν+ hμν,    hμν~ ei(ωt - kx)",
        "category": "other",
        "file": "sections/cosmology.html",
        "action": "REVIEW",
        "reason": "Needs manual review",
        "simulation_backed": false
      },
      {
        "formula": "FR&Boxhμν+ (FT+ δ ∂τ)T(1)μν= 0",
        "category": "other",
        "file": "sections/cosmology.html",
        "action": "REVIEW",
        "reason": "Needs manual review",
        "simulation_backed": false
      },
      {
        "formula": "(-ω2+ k2)FR+ (β + δ ω) ω2= 0",
        "category": "other",
        "file": "sections/cosmology.html",
        "action": "REVIEW",
        "reason": "Needs manual review",
        "simulation_backed": false
      },
      {
        "formula": "ω2= k2[1 + ξ2(k/MPl)2+ η k Δtortho/c](6.15a)",
        "category": "other",
        "file": "sections/cosmology.html",
        "action": "REVIEW",
        "reason": "Needs manual review",
        "simulation_backed": false
      },
      {
        "formula": "LISA sensitivity: δω/ω ~ 10-20at f ~ 10-3Hz",
        "category": "other",
        "file": "sections/cosmology.html",
        "action": "REVIEW",
        "reason": "Needs manual review",
        "simulation_backed": false
      },
      {
        "formula": "⟨OA(t) OB(0)⟩β= ⟨OB(0) OA(t + iβ)⟩β",
        "category": "other",
        "file": "sections/cosmology.html",
        "action": "REVIEW",
        "reason": "Needs manual review",
        "simulation_backed": false
      },
      {
        "formula": "⟨ΨP(tth, to) ΨP†(0,0)⟩ = ⟨ΨP†(0,0) ΨP(tth+ iβth, to+ iβo)⟩(6.15b)",
        "category": "other",
        "file": "sections/cosmology.html",
        "action": "REVIEW",
        "reason": "Needs manual review",
        "simulation_backed": false
      },
      {
        "formula": "K = Htherm+ αTTHortho",
        "category": "other",
        "file": "sections/cosmology.html",
        "action": "REVIEW",
        "reason": "Needs manual review",
        "simulation_backed": false
      },
      {
        "formula": "Γ(Eth, Eo) = e-βthEth- βoEoΓ(-Eth, -Eo)",
        "category": "other",
        "file": "sections/cosmology.html",
        "action": "REVIEW",
        "reason": "Needs manual review",
        "simulation_backed": false
      },
      {
        "formula": "Stotal= Stherm+ Sortho≥ 0   →   dStotal/dttherm> 0",
        "category": "other",
        "file": "sections/cosmology.html",
        "action": "REVIEW",
        "reason": "Needs manual review",
        "simulation_backed": false
      },
      {
        "formula": "Hphys= Ker(Q)/Im(Q)     Q2= 0(6.17)",
        "category": "other",
        "file": "sections/cosmology.html",
        "action": "REVIEW",
        "reason": "Needs manual review",
        "simulation_backed": false
      },
      {
        "formula": "[Q, H] = 0    ⇒    S-matrix is unitary on Hphys(6.18)",
        "category": "other",
        "file": "sections/cosmology.html",
        "action": "REVIEW",
        "reason": "Needs manual review",
        "simulation_backed": false
      },
      {
        "formula": "SPneuma/V ≤ Nmodes× log(2)/V ∼ 1/lPneuma3(6.19)",
        "category": "other",
        "file": "sections/cosmology.html",
        "action": "REVIEW",
        "reason": "Needs manual review",
        "simulation_backed": false
      },
      {
        "formula": "FR> 0    (no graviton ghost)    \n            FRR> 0    (no scalaron ghost)(6.20)",
        "category": "other",
        "file": "sections/cosmology.html",
        "action": "REVIEW",
        "reason": "Needs manual review",
        "simulation_backed": false
      },
      {
        "formula": "D = 13 = 1 + 4 + 8 = dim(R) + dim(H) + dim(O)The unique division algebra decomposition of D = 13",
        "category": "other",
        "file": "sections/division-algebra-section.html",
        "action": "REVIEW",
        "reason": "Needs manual review",
        "simulation_backed": false
      },
      {
        "formula": "dim(F4) = 52 = 4 × 13Automorphisms of J3(O)dim(E6) = 78 = 6 × 13Collineations ofOP2dim(J3(O)) - dim(",
        "category": "other",
        "file": "sections/division-algebra-section.html",
        "action": "REVIEW",
        "reason": "Needs manual review",
        "simulation_backed": false
      },
      {
        "formula": "F(R,T,τ) = R + αT + βT² + γτ + δτ²Modified gravity function with torsion coupling",
        "category": "other",
        "file": "sections/einstein-hilbert-term.html",
        "action": "REVIEW",
        "reason": "Needs manual review",
        "simulation_backed": false
      },
      {
        "formula": "F(R,T,τ) = R + αT + βT² + γτ + δτ²Modified gravity function (canonical form)",
        "category": "other",
        "file": "sections/einstein-hilbert-term.html",
        "action": "REVIEW",
        "reason": "Needs manual review",
        "simulation_backed": false
      },
      {
        "formula": "Λeff= (γτ + δτ²)/2Effective cosmological constant from torsion",
        "category": "other",
        "file": "sections/einstein-hilbert-term.html",
        "action": "REVIEW",
        "reason": "Needs manual review",
        "simulation_backed": false
      },
      {
        "formula": "mgen(n)= m0· e−n·d/ℓ(n = 1, 2, 3)",
        "category": "other",
        "file": "sections/fermion-sector.html",
        "action": "REVIEW",
        "reason": "Needs manual review",
        "simulation_backed": false
      },
      {
        "formula": "Ind(D) = (1/24π²) ∫Σ³Tr(F∧F)Atiyah-Singer index for Dirac operator on 3-cycle Σ³",
        "category": "other",
        "file": "sections/fermion-sector.html",
        "action": "REVIEW",
        "reason": "Needs manual review",
        "simulation_backed": false
      },
      {
        "formula": "tGUT= log(MGUT/TeV) ≈ 30   ⇒   MGUT≈ 1013TeVGUT scale from RG flow parameter",
        "category": "other",
        "file": "sections/gauge-unification.html",
        "action": "REVIEW",
        "reason": "Needs manual review",
        "simulation_backed": false
      },
      {
        "formula": "ln(MPl/MGUT,base) = ln(1.22×1019/1.8×1016) = ln(677.8) =6.519Logarithmic scale separation",
        "category": "other",
        "file": "sections/gauge-unification.html",
        "action": "REVIEW",
        "reason": "Needs manual review",
        "simulation_backed": false
      },
      {
        "formula": "s = [ln(MPl/MGUT,base) - Tω] / NfluxWarping parameter",
        "category": "other",
        "file": "sections/gauge-unification.html",
        "action": "REVIEW",
        "reason": "Needs manual review",
        "simulation_backed": false
      },
      {
        "formula": "s = (6.519 - (-0.8836)) / 6.283 = 7.403 / 6.283 =1.178Numerical evaluation: s ≈ 1.18",
        "category": "other",
        "file": "sections/gauge-unification.html",
        "action": "REVIEW",
        "reason": "Needs manual review",
        "simulation_backed": false
      },
      {
        "formula": "MGUT= 1.8×1016GeV × (1 + 0.15 × 1.178)= 1.8×1016GeV × (1 + 0.1767)= 1.8×1016GeV × 1.1767=GeVFinal re",
        "category": "other",
        "file": "sections/gauge-unification.html",
        "action": "REVIEW",
        "reason": "Needs manual review",
        "simulation_backed": false
      },
      {
        "formula": "Uncertainty: ΔMGUT= ±0.09 × 1016GeV   (4.3% relative error)Error from b₃ flux variations",
        "category": "other",
        "file": "sections/gauge-unification.html",
        "action": "REVIEW",
        "reason": "Needs manual review",
        "simulation_backed": false
      },
      {
        "formula": "The K3 surfaces S₊ and S₋ at asymptotic infinity have Picard lattices N₊ and N₋\n                    ",
        "category": "other",
        "file": "sections/geometric-framework.html",
        "action": "REVIEW",
        "reason": "Needs manual review",
        "simulation_backed": false
      },
      {
        "formula": "Hover for detailsρB1ρB1The reduced density matrix on our brane - the quantum state we actually obser",
        "category": "other",
        "file": "sections/geometric-framework.html",
        "action": "REVIEW",
        "reason": "Needs manual review",
        "simulation_backed": false
      }
    ]
  }
}