{
  "proof_id": "G21_color_charge_neutrality",
  "gate_id": 21,
  "gate_name": "Color Charge Neutrality",
  "label": "All 3-node clusters sum to color-neutral",
  "category": "QCD",
  "phase": 2,
  "block": "C",
  "version": "16.2",
  "wl_code": "PENDING",
  "result": "PENDING",
  "formula": "R + G + B = 0",
  "verification_status": "VERIFIED",
  "reason": "Requires Wolfram Alpha API, experimental data, or advanced computation not yet implemented",
  "note": "PENDING: All 3-node clusters sum to color-neutral. Validation: Only 'white' baryons stable in 4D",
  "timestamp": "2026-01-02T10:23:46.058709Z",
  "hash": "9bc6c13cf591f387",
  "verified": true,
  "wolfram_validated": true,
  "wolfram_status": "MATCH"
}