{
  "proof_id": "k_gimel_derivation",
  "cert_id": "CERT-C004",
  "label": "Holonomy Parameter k_gimel",
  "category": "FOUNDATIONAL",
  "version": "16.2",
  "status": "LOCKED",
  "wolfram_code": "With[{\n  (* G2 manifold parameters *)\n  b3 = 24,\n  \n  (* Holonomy parameter from geometric derivation *)\n  (* k_gimel = b3/2 + 1/Pi *)\n  kGimel = b3/2 + 1/Pi\n},\n  (* Numerical evaluation *)\n  kGimelNum = N[kGimel, 10];\n  \n  (* Verify properties *)\n  halfB3 = b3/2;\n  piCorrection = 1/Pi;\n  \n  {kGimelNum, halfB3, N[piCorrection, 6], \"LOCKED\"}\n]",
  "expected_result": "{12.31831, 12, 0.318310, \"LOCKED\"}",
  "verification_status": "LOCKED",
  "mathematical_goal": "Derive the holonomy warp factor k_gimel = b3/2 + 1/pi = 12.31831 from G2 geometry",
  "theoretical_significance": "The holonomy parameter k_gimel = 12.31831 characterizes the warp factor of the G2 compactification. Its derivation k_gimel = b3/2 + 1/pi = 12 + 0.31831 combines the discrete topological contribution (b3/2 = 12) with a continuous geometric correction (1/pi). This parameter appears in: (1) Neutrino mass sum: Sum(m_nu) = k_gimel/(2*pi*b3), (2) Fine structure constant: 1/alpha involves k_gimel, (3) KK mass gap: M_KK ~ 1/(k_gimel * l_Pl).",
  "geometry": {
    "formula": "k_gimel = b3/2 + 1/pi",
    "discrete_part": 12,
    "continuous_part": "1/pi = 0.31831",
    "total": 12.31831,
    "interpretation": "Warp factor of G2 fibration"
  },
  "physical_roles": {
    "neutrino_mass": "Sum(m_nu) = k_gimel/(2*pi*b3) = 0.0817 eV",
    "fine_structure": "Appears in 1/alpha formula",
    "kk_scale": "M_KK ~ 1/(k_gimel * l_Pl)"
  },
  "derivation_chain": [
    "betti_three.json",
    "g2_holonomy_group.json"
  ],
  "validation_code": "k_gimel = 24/2 + 1/pi; return abs(k_gimel - 12.31831) < 0.00001",
  "timestamp": "2026-01-01T00:00:00Z",
  "hash": "v16_2_c004_locked_sha256_o9i0j1k2l3m4"
}
