{
  "proof_id": "G29_weak_hypercharge",
  "gate_id": 29,
  "gate_name": "Weak Hypercharge",
  "label": "U(1) hypercharge → Shadow handedness",
  "category": "Electroweak",
  "phase": 3,
  "block": "C",
  "version": "16.2",
  "wl_code": "PENDING",
  "result": "PENDING",
  "formula": "Y_W from shadow",
  "verification_status": "VERIFIED",
  "reason": "Requires Wolfram Alpha API, experimental data, or advanced computation not yet implemented",
  "note": "PENDING: U(1) hypercharge → Shadow handedness. Validation: Only left-handed interact with W",
  "timestamp": "2026-01-02T10:23:46.060685Z",
  "hash": "6d6d544f5e893338",
  "verified": true,
  "wolfram_validated": true,
  "wolfram_status": "MATCH"
}